Metadata-Version: 2.4
Name: distributed-ucxx-cu12
Version: 0.47.0
Summary: UCX communication module for Dask Distributed
Author: NVIDIA Corporation
License: BSD-3-Clause
Project-URL: Homepage, https://github.com/rapidsai/ucxx
Project-URL: Documentation, https://distributed.dask.org/
Project-URL: Source, https://github.com/rapidsai/ucxx
Classifier: Intended Audience :: Developers
Classifier: License :: OSI Approved :: Apache Software License
Classifier: Programming Language :: Python :: 3
Classifier: Programming Language :: Python :: 3.10
Classifier: Programming Language :: Python :: 3.11
Classifier: Programming Language :: Python :: 3.12
Classifier: Programming Language :: Python :: 3.13
Requires-Python: >=3.10
License-File: LICENSE
Requires-Dist: numba-cuda[cu12]<0.20.0a0,>=0.19.1
Requires-Dist: pyyaml>=6
Requires-Dist: rapids-dask-dependency==25.12.*
Requires-Dist: ucxx-cu12==0.47.*
Provides-Extra: docs
Requires-Dist: sphinx; extra == "docs"
Requires-Dist: sphinx-click>=2.7.1; extra == "docs"
Requires-Dist: sphinx-rtd-theme>=0.5.1; extra == "docs"
Provides-Extra: test
Requires-Dist: cudf-cu12==25.12.*; extra == "test"
Requires-Dist: cupy-cuda12x>=13.6.0; extra == "test"
Requires-Dist: numpy<3.0a0,>=1.23; extra == "test"
Requires-Dist: pytest-rerunfailures!=16.0.0; extra == "test"
Requires-Dist: pytest<9.0.0a0; extra == "test"
Dynamic: license-file
